deeppavlov/__init__.py
deeppavlov/__main__.py
deeppavlov/_meta.py
deeppavlov/deep.py
deeppavlov/download.py
deeppavlov/paramsearch.py
deeppavlov/settings.py
deeppavlov/configs/__init__.py
deeppavlov/configs/classifiers/boolqa_rubert.json
deeppavlov/configs/classifiers/few_shot_roberta.json
deeppavlov/configs/classifiers/insults_kaggle_bert.json
deeppavlov/configs/classifiers/paraphraser_convers_distilrubert_2L.json
deeppavlov/configs/classifiers/paraphraser_convers_distilrubert_6L.json
deeppavlov/configs/classifiers/paraphraser_rubert.json
deeppavlov/configs/classifiers/query_pr.json
deeppavlov/configs/classifiers/rusentiment_bert.json
deeppavlov/configs/classifiers/rusentiment_convers_bert.json
deeppavlov/configs/classifiers/rusentiment_convers_distilrubert_2L.json
deeppavlov/configs/classifiers/rusentiment_convers_distilrubert_6L.json
deeppavlov/configs/classifiers/sentiment_sst_conv_bert.json
deeppavlov/configs/classifiers/sentiment_twitter.json
deeppavlov/configs/classifiers/topics_distilbert_base_uncased.json
deeppavlov/configs/classifiers/glue/glue_cola_roberta.json
deeppavlov/configs/classifiers/glue/glue_mnli_cased_bert_torch.json
deeppavlov/configs/classifiers/glue/glue_mnli_mm_cased_bert_torch.json
deeppavlov/configs/classifiers/glue/glue_mnli_roberta.json
deeppavlov/configs/classifiers/glue/glue_mrpc_roberta.json
deeppavlov/configs/classifiers/glue/glue_qnli_roberta.json
deeppavlov/configs/classifiers/glue/glue_qqp_roberta.json
deeppavlov/configs/classifiers/glue/glue_rte_cased_bert_torch.json
deeppavlov/configs/classifiers/glue/glue_rte_roberta_mnli.json
deeppavlov/configs/classifiers/glue/glue_sst2_roberta.json
deeppavlov/configs/classifiers/glue/glue_stsb_roberta.json
deeppavlov/configs/classifiers/glue/glue_wnli_roberta.json
deeppavlov/configs/classifiers/superglue/superglue_boolq_roberta_mnli.json
deeppavlov/configs/classifiers/superglue/superglue_copa_roberta.json
deeppavlov/configs/classifiers/superglue/superglue_record_roberta.json
deeppavlov-1.7.0.dist-info/LICENSE
deeppavlov-1.7.0.dist-info/METADATA
deeppavlov-1.7.0.dist-info/WHEEL
deeppavlov-1.7.0.dist-info/top_level.txt
deeppavlov-1.7.0.dist-info/RECORD
