Metadata-Version: 2.1
Name: deeppavlov
Version: 1.7.0
Summary: An open source library for building end-to-end dialog systems and training chatbots.
Home-page: https://github.com/deeppavlov/DeepPavlov
Download-URL: https://github.com/deeppavlov/DeepPavlov/archive/1.7.0.tar.gz
Author: Neural Networks and Deep Learning lab, MIPT
Author-email: info@deeppavlov.ai
License: Apache License, Version 2.0
Keywords: NLP,NER,SQUAD,Intents,Chatbot
License-File: LICENSE
Requires-Dist: fastapi<=0.89.1,>=0.47.0
Requires-Dist: filelock<3.10.0,>=3.0.0
Requires-Dist: nltk<3.10.0,>=3.2.4
Requires-Dist: numpy<1.24
Requires-Dist: pandas<1.6.0,>=1.0.0
Requires-Dist: prometheus-client<=1.16.0,>=0.13.0
Requires-Dist: pydantic<2
Requires-Dist: pybind11==2.10.3
Requires-Dist: requests<3.0.0,>=2.19.0
Requires-Dist: scikit-learn<1.1.0,>=0.24; python_version <= "3.10"
Requires-Dist: scikit-learn==1.4.0; python_version == "3.11.*"
Requires-Dist: tqdm<4.65.0,>=4.42.0
Requires-Dist: uvicorn<0.19.0,>=0.13.0
Requires-Dist: wheel
Requires-Dist: scipy<1.10.0; python_version < "3.8"
Requires-Dist: scipy==1.10.0; python_version >= "3.8"
Provides-Extra: tests
Requires-Dist: flake8; extra == "tests"
Requires-Dist: pytest; extra == "tests"
Requires-Dist: pytest-instafail; extra == "tests"
Requires-Dist: pexpect; extra == "tests"
Provides-Extra: docs
Requires-Dist: sphinx==3.5.4; python_version <= "3.7" and extra == "docs"
Requires-Dist: sphinx==5.0.0; python_version == "3.8" and extra == "docs"
Requires-Dist: sphinx==5.0.0; python_version == "3.9" and extra == "docs"
Requires-Dist: sphinx==5.0.0; python_version == "3.10" and extra == "docs"
Requires-Dist: sphinx==7.2.*; python_version == "3.11.*" and extra == "docs"
Requires-Dist: sphinx_rtd_theme==0.5.2; python_version <= "3.10" and extra == "docs"
Requires-Dist: sphinx_rtd_theme==2.0.0; python_version == "3.11.*" and extra == "docs"
Requires-Dist: docutils<0.17,>=0.12; python_version <= "3.10" and extra == "docs"
Requires-Dist: docutils==0.20.1; python_version == "3.11.*" and extra == "docs"
Requires-Dist: nbsphinx==0.8.4; python_version <= "3.10" and extra == "docs"
Requires-Dist: nbsphinx==0.9.3; python_version == "3.11.*" and extra == "docs"
Requires-Dist: ipykernel==5.5.4; extra == "docs"
Requires-Dist: jinja2<=3.0.3; extra == "docs"
Requires-Dist: sphinx-copybutton==0.5.0; extra == "docs"
Requires-Dist: pandoc==2.3; extra == "docs"
Requires-Dist: ipython_genutils==0.2.0; extra == "docs"
Provides-Extra: s3
Requires-Dist: boto3; extra == "s3"
